README.md
setup.py
dutool/__init__.py
dutool/models.py
dutool.egg-info/PKG-INFO
dutool.egg-info/SOURCES.txt
dutool.egg-info/dependency_links.txt
dutool.egg-info/requires.txt
dutool.egg-info/top_level.txt