Metadata-Version: 1.0
Name: dutool
Version: 0.0.3
Summary: a library for revang developer
Home-page: https://github.com/revang/dutool
Author: revang
Author-email: revang.alternative@foxmail.com
License: MIT License
Keywords: dutool
Platform: any
